selenium_project/__init__.py
selenium_project/main.py
selenium_project/data/__init__.py
selenium_project/data/data_process.py
selenium_project/data/data_read.py
selenium_project/data/test_data.py
selenium_project/lib/__init__.py
selenium_project/logs/__init__.py
selenium_project/logs/log_test.py
selenium_project/reports/__init__.py
selenium_project/screenshots/__init__.py
selenium_project/testcases/ActionChains_click.py
selenium_project/testcases/__init__.py
selenium_project/testcases/get_data.py
selenium_project/testcases/test_01_register.py
selenium_project/testcases/test_02_chrome_continue.py
selenium_project/testcases/test_03_classify.py
selenium_project/testcases/test_04_write_articles.py
selenium_project/testcases/test_05_delete_article.py
selenium_project/testcases/test_06_changeOPConfig.py
selenium_project/util/__init__.py
selenium_project/util/get2fa.py
selenium_project/util/util.py
selenium_auto_executor-1.0.3.dist-info/METADATA
selenium_auto_executor-1.0.3.dist-info/WHEEL
selenium_auto_executor-1.0.3.dist-info/top_level.txt
selenium_auto_executor-1.0.3.dist-info/RECORD
