Metadata-Version: 2.1
Name: selenium-auto-executor
Version: 1.0.3
Summary: selenium_auto_executor
Home-page: UNKNOWN
Author: XB605324585
Author-email: XB605324585@gmail.com
License: UNKNOWN
Platform: UNKNOWN
Requires-Dist: allure-pytest ==2.13.2
Requires-Dist: allure-python-commons ==2.13.2
Requires-Dist: attrs ==23.1.0
Requires-Dist: beautifulsoup4 ==4.9.3
Requires-Dist: cachetools ==4.2.1
Requires-Dist: certifi ==2023.11.17
Requires-Dist: cffi ==1.16.0
Requires-Dist: chardet ==4.0.0
Requires-Dist: charset-normalizer ==3.3.2
Requires-Dist: colorama ==0.4.6
Requires-Dist: coloredlogs ==15.0.1
Requires-Dist: crcmod ==1.7
Requires-Dist: crypto ==1.4.1
Requires-Dist: ddddocr ==1.4.10
Requires-Dist: ddt ==1.7.0
Requires-Dist: docutils ==0.20.1
Requires-Dist: et-xmlfile ==1.1.0
Requires-Dist: exceptiongroup ==1.2.0
Requires-Dist: flatbuffers ==23.5.26
Requires-Dist: google ==3.0.0
Requires-Dist: google-api-core ==1.26.3
Requires-Dist: google-auth ==1.29.0
Requires-Dist: google-cloud-core ==1.6.0
Requires-Dist: google-cloud-storage ==1.37.1
Requires-Dist: google-crc32c ==1.1.2
Requires-Dist: google-resumable-media ==1.2.0
Requires-Dist: googleapis-common-protos ==1.53.0
Requires-Dist: h11 ==0.14.0
Requires-Dist: humanfriendly ==10.0
Requires-Dist: idna ==3.4
Requires-Dist: importlib-metadata ==7.0.1
Requires-Dist: importlib-resources ==6.1.1
Requires-Dist: incremental ==21.3.0
Requires-Dist: iniconfig ==2.0.0
Requires-Dist: jaraco.classes ==3.3.1
Requires-Dist: keyring ==24.3.0
Requires-Dist: markdown-it-py ==3.0.0
Requires-Dist: mdurl ==0.1.2
Requires-Dist: more-itertools ==10.2.0
Requires-Dist: MouseInfo ==0.1.3
Requires-Dist: mpmath ==1.3.0
Requires-Dist: Naked ==0.1.31
Requires-Dist: nh3 ==0.2.15
Requires-Dist: numpy ==1.24.4
Requires-Dist: onnxruntime ==1.16.3
Requires-Dist: opencv-python-headless ==4.8.1.78
Requires-Dist: openpyxl ==3.1.2
Requires-Dist: outcome ==1.3.0.post0
Requires-Dist: packaging ==23.2
Requires-Dist: pandas ==2.0.3
Requires-Dist: parameterized ==0.9.0
Requires-Dist: Pillow ==10.1.0
Requires-Dist: pkginfo ==1.9.6
Requires-Dist: pluggy ==1.3.0
Requires-Dist: protobuf ==4.25.1
Requires-Dist: pyasn1 ==0.4.8
Requires-Dist: pyasn1-modules ==0.2.8
Requires-Dist: PyAutoGUI ==0.9.54
Requires-Dist: pycparser ==2.21
Requires-Dist: pycryptodome ==3.10.1
Requires-Dist: pyDes ==2.0.1
Requires-Dist: PyGetWindow ==0.0.9
Requires-Dist: Pygments ==2.17.2
Requires-Dist: PyMsgBox ==1.0.9
Requires-Dist: pyotp ==2.9.0
Requires-Dist: pyparsing ==2.4.7
Requires-Dist: pyperclip ==1.8.2
Requires-Dist: pyreadline3 ==3.4.1
Requires-Dist: PyRect ==0.2.0
Requires-Dist: PyScreeze ==0.1.30
Requires-Dist: PySocks ==1.7.1
Requires-Dist: pytesseract ==0.3.10
Requires-Dist: pytest ==7.4.3
Requires-Dist: python-dateutil ==2.8.2
Requires-Dist: pytweening ==1.0.7
Requires-Dist: pytz ==2023.3.post1
Requires-Dist: pywin32 ==306
Requires-Dist: pywin32-ctypes ==0.2.2
Requires-Dist: PyYAML ==5.4.1
Requires-Dist: readme-renderer ==42.0
Requires-Dist: requests ==2.31.0
Requires-Dist: requests-toolbelt ==1.0.0
Requires-Dist: rfc3986 ==2.0.0
Requires-Dist: rich ==13.7.0
Requires-Dist: rsa ==4.7.2
Requires-Dist: selenium ==4.15.2
Requires-Dist: shadowsocks ==2.8.2
Requires-Dist: shellescape ==3.8.1
Requires-Dist: six ==1.16.0
Requires-Dist: sniffio ==1.3.0
Requires-Dist: sortedcontainers ==2.4.0
Requires-Dist: soupsieve ==2.2.1
Requires-Dist: sympy ==1.12
Requires-Dist: tomli ==2.0.1
Requires-Dist: trio ==0.23.1
Requires-Dist: trio-websocket ==0.11.1
Requires-Dist: twine ==4.0.2
Requires-Dist: typing-extensions ==4.9.0
Requires-Dist: tzdata ==2023.3
Requires-Dist: urllib3 ==2.1.0
Requires-Dist: wsproto ==1.2.0
Requires-Dist: xlrd ==2.0.1
Requires-Dist: zipp ==3.17.0
